rdf2vecgpu/__init__.py
rdf2vecgpu/gpu_rdf2vec.py
rdf2vecgpu/corpus/__init__.py
rdf2vecgpu/corpus/walk_corpus.py
rdf2vecgpu/embedders/__init__.py
rdf2vecgpu/embedders/word2vec.py
rdf2vecgpu/embedders/word2vec_loader.py
rdf2vecgpu/helper/__init__.py
rdf2vecgpu/helper/functions.py
rdf2vecgpu/logger/__init__.py
rdf2vecgpu/logger/base.py
rdf2vecgpu/logger/mlflow_logger.py
rdf2vecgpu/logger/wandb_logger.py
rdf2vecgpu/reader/__init__.py
rdf2vecgpu/reader/kg_file_reader.py
rdf2vecgpu/reader/kg_reader.py
rdf2vecgpu-0.2.3.dist-info/METADATA
rdf2vecgpu-0.2.3.dist-info/WHEEL
rdf2vecgpu-0.2.3.dist-info/licenses/LICENSE
rdf2vecgpu-0.2.3.dist-info/RECORD
