Metadata-Version: 2.4
Name: rdf2vecgpu
Version: 0.2.3
Summary: GPU-Accelerated RDF2Vec – A high-performance GPU implementation of RDF2Vec that uses CUDA and RAPIDS to generate scalable, embeddings for large dense knowledge graphs.
Project-URL: Homepage, https://github.com/MartinBoeckling/rdf2vecgpu
Project-URL: Issues, https://github.com/MartinBoeckling/rdf2vecgpu/issues
License: MIT
License-File: LICENSE
Requires-Python: >=3.12
Requires-Dist: cudf-cu12>=25.6.0
Requires-Dist: cugraph-cu12==25.6.*
Requires-Dist: cupy-cuda12x>=13.5.1
Requires-Dist: dask-cudf-cu12>=25.6.0
Requires-Dist: dask[complete]>=2025.5.0
Requires-Dist: lightning>=2.5.2
Requires-Dist: loguru>=0.7.3
Requires-Dist: numpy>=2.2.6
Requires-Dist: rdflib>=7.1.4
Requires-Dist: torch>=2.7.1
Requires-Dist: tqdm>=4.67.1
Provides-Extra: mlflow
Requires-Dist: mlflow>=3.5.1; extra == 'mlflow'
